pysgems/__init__.py
pysgems/algo/__init__.py
pysgems/algo/sgalgo.py
pysgems/algorithms/Variogram_model.xml
pysgems/algorithms/full_indicator_kriging.xml
pysgems/algorithms/full_indicator_kriging_postKriging.xml
pysgems/algorithms/kriging.xml
pysgems/algorithms/sgsim.xml
pysgems/base/__init__.py
pysgems/base/packbase.py
pysgems/dis/.DS_Store
pysgems/dis/__init__.py
pysgems/dis/sgdis.py
pysgems/examples/__init__.py
pysgems/examples/demo_indicator_kriging.py
pysgems/examples/demo_indicator_kriging_mapping.py
pysgems/examples/demo_kriging.py
pysgems/examples/demo_sgsim.py
pysgems/examples/datasets/demo_indicator_kriging/VMM_PFOA_PFOS_EFSA4_Drinkwater20_2d.csv
pysgems/examples/datasets/demo_indicator_kriging/sgems_dataset_full_indicator_kriging.eas
pysgems/examples/datasets/demo_kriging/sgems_dataset.eas
pysgems/examples/datasets/demo_sgsim/sgsim_hard_data.eas
pysgems/examples/datasets/demo_sgsim3D/sgsim_hard_data3D.eas
pysgems/io/.DS_Store
pysgems/io/__init__.py
pysgems/io/sgio.py
pysgems/plot/__init__.py
pysgems/plot/sgplots.py
pysgems/script_templates/script_template.py
pysgems/script_templates/script_template_FIK.py
pysgems/sgems/.DS_Store
pysgems/sgems/__init__.py
pysgems/sgems/sg.py
pysgems/utils/__init__.py
pysgems/utils/sgutils.py
pysgems-1.2.3.dist-info/LICENSE
pysgems-1.2.3.dist-info/METADATA
pysgems-1.2.3.dist-info/WHEEL
pysgems-1.2.3.dist-info/top_level.txt
pysgems-1.2.3.dist-info/RECORD
