Metadata-Version: 2.1
Name: pysgems
Version: 1.2.3
Summary: Use SGeMS (Stanford Geostatistical Modeling Software) within Python.
Home-page: https://github.com/robinthibaut/pysgems
Author: Robin Thibaut
Author-email: robin.thibaut@UGent.be
License: MIT
Classifier: Programming Language :: Python :: 3
Classifier: License :: OSI Approved :: MIT License
Classifier: Operating System :: OS Independent
License-File: LICENSE
Requires-Dist: numpy
Requires-Dist: pandas
Requires-Dist: scipy
Requires-Dist: matplotlib
Requires-Dist: loguru
